django_sass_finder/__init__.py
django_sass_finder/finders.py
django_sass_finder-2.0.7.dist-info/LICENSE
django_sass_finder-2.0.7.dist-info/WHEEL
django_sass_finder-2.0.7.dist-info/METADATA
django_sass_finder-2.0.7.dist-info/RECORD
